Workbook
Name a: 'Optimización Ventas'!$H$35
Name Accesories: 'Optimización Ventas'!$E$26
Name ads: 'Optimización Ventas'!$H$35
Name asdasdas: 'Optimización Ventas'!$H$35
Name b: 'Optimización Ventas'!$H$35
Name Bikes: 'Optimización Ventas'!$F$26
Name Cant_Accessories: 'Optimización Ventas'!$E$27
Name Cant_Bikes: 'Optimización Ventas'!$F$27
Name Cant_Clothing: 'Optimización Ventas'!$G$27
Name CANTIDAD: 'Optimización Ventas'!$H$35
Name Cantidad_Accesories: 'Optimización Ventas'!$H$35
Name Cantidad_Accessories: 'Optimización Ventas'!$H$35
Name Cantidad_Accessories: 'Optimización Ventas'!$H$35
Name Cantidad_Bikes: 'Optimización Ventas'!$H$36
Name Cantidad_Clothing: 'Optimización Ventas'!$H$37
Name Clothing: 'Optimización Ventas'!$G$26
Name Max_Accessories: 'Optimización Ventas'!$H$35
Name Maxi_Accessories: 'Optimización Ventas'!$H$35
Name Maximo: 'Optimización Ventas'!$H$35
Name Maximo_Accessories: 'Optimización Ventas'!$H$35
Name Maximo_Bikes: 'Optimización Ventas'!$H$36
Name Min_Accessories: 'Optimización Ventas'!$H$38
Name Minimo_a: 'Optimización Ventas'!$H$35
Name Minimo_Accessories: 'Optimización Ventas'!$H$35
Name Minimo_Bikes: 'Optimización Ventas'!$H$39
Name Minimo_Cantidad_Accessories: 'Optimización Ventas'!$H$35
Name Minimo_Clothing: 'Optimización Ventas'!$H$40
Name nose: 'Optimización Ventas'!$H$38
Name SegmentaciónDeDatos_categoria: #N/A
Name Timeline_fecha_entrega: #N/A

Sheet informacion
A3: Fecha | B3: Cantidad Pedidos | D3: Etiquetas de fila | E3: Cantidad Pedidos | G3: Etiquetas de fila | H3: Importe Total
A4: 40548 | B4: 5 | D4: Mason Roberts | E4: 28 | G4: Jordan Turner | H4: 15998
A5: 40549 | B5: 4 | D5: Dalton Perez | E5: 28 | G5: Willie Xu | H5: 13489
A6: 40550 | B6: 5 | D6: Ryan Thompson | E6: 27 | G6: Nichole Nara | H6: 13294
A7: 40551 | B7: 2 | D7: Samantha Jenkins | E7: 27 | G7: Kaitlyn Henderson | H7: 13294
A8: 40552 | B8: 5 | D8: Nancy Chapman | E8: 27 | G8: Margaret He | H8: 13268
A9: 40553 | B9: 4 | D9: Hailey Patterson | E9: 27 | G9: Randall Dominguez | H9: 13265
A10: 40554 | B10: 3 | D10: Jennifer Simmons | E10: 27 | G10: Adriana Gonzalez | H10: 13242
A11: 40555 | B11: 3 | D11: Jason Griffin | E11: 27 | G11: Rosa Hu | H11: 13215
A12: 40556 | B12: 6 | D12: Daniel Davis | E12: 27 | G12: Brandi Gill | H12: 13195
A13: 40557 | B13: 3 | D13: Fernando Barnes | E13: 27 | G13: Brad She | H13: 13172
A14: 40558 | B14: 4 | D14: Henry Garcia | E14: 27 | G14: Francisco Sara | H14: 13164
A15: 40559 | B15: 4 | D15: Ashley Henderson | E15: 27 | G15: Maurice Shan | H15: 12914
... A1127: 41674 | B1127: 40 | D1127: Jenny Lal | E1127: 3 | G1127: Jenny Rai | H1127: 5955
A1128: Total general | B1128: 27659 | D1128: Dennis Zeng | E1128: 3 | G1128: Cody Cook | H1128: 5955
D1129: Donna Deng | E1129: 3 | G1129: Ariana Sanchez | H1129: 5955
D1130: Gina Romero | E1130: 3 | G1130: Daniel Garcia | H1130: 5954
D1131: Jeremiah Griffin | E1131: 3 | G1131: Hunter Griffin | H1131: 5954
D1132: Glenn Lu | E1132: 3 | G1132: Dominique Sanchez | H1132: 5954
D1133: Jeremiah Johnson | E1133: 3 | G1133: Wendy Ramos | H1133: 5953
D1134: Glenn Wang | E1134: 3 | G1134: Mary Patterson | H1134: 5953
D1135: Jeremy Powell | E1135: 3 | G1135: Natalie Adams | H1135: 5953
D1136: Glenn Zhang | E1136: 3 | G1136: Gabriel Green | H1136: 5953
D1137: Jermaine Lopez | E1137: 3 | G1137: Brendan Chande | H1137: 5953
D1138: Gloria Carlson | E1138: 3 | G1138: Tristan Ross | H1138: 5951
D1139: Jerome Romero | E1139: 3 | G1139: Sophia Wright | H1139: 5950
D1140: Gloria Ruiz | E1140: 3 | G1140: Virginia Sara | H1140: 5950
... D18403: Total general | E18403: 27659 | G18403: Total general | H18403: 29356250

Sheet Reporte Escenarios
B1: ESCENARIOS DE VENTAS PARA EL AÑO 2014
B5: ESCENARIO AGRESIVO | H5: ESCENARIO OBJETIVO | N5: ESCENARIO MODESTO
B6: Categoría | C6: Cantidad | D6: Precio | E6: Ventas | H6: Categoría | I6: Cantidad | J6: Precio | K6: Ventas | N6: Categoría | O6: Cantidad | P6: Precio | Q6: Ventas
B7: {=_xlfn.ANCHORARRAY('Optimización Ventas'!$A$27)} -> Accessories | C7: {='Escenario Agresivo'!E21:E23} -> 1000 | D7: {=_xlfn.ANCHORARRAY('Optimización Ventas'!$B$27)} -> 10 | E7: =C7*D7 -> 10000 | H7: {=_xlfn.ANCHORARRAY('Optimización Ventas'!$A$27)} -> Accessories | I7: {='Escenario Objetivo'!E21:E23} -> 1000 | J7: {=_xlfn.ANCHORARRAY('Optimización Ventas'!$B$27)} -> 10 | K7: =I7*J7 -> 10000 | N7: {=_xlfn.ANCHORARRAY('Optimización Ventas'!$A$27)} -> Accessories | O7: {='Escenario Modesto'!E21:E23} -> 1000 | P7: {=_xlfn.ANCHORARRAY('Optimización Ventas'!$B$27)} -> 10 | Q7: =O7*P7 -> 10000
B8: Bikes | C8: 11150 | D8: 713 | E8: =C8*D8 -> 7949950 | H8: Bikes | I8: 9750 | J8: 713 | K8: =I8*J8 -> 6951750 | N8: Bikes | O8: 8350 | P8: 713 | Q8: =O8*P8 -> 5953550
B9: Clothing | C9: 1602 | D9: 25 | E9: =C9*D9 -> 40050 | H9: Clothing | I9: 1530 | J9: 25 | K9: =I9*J9 -> 38250 | N9: Clothing | O9: 1458 | P9: 25 | Q9: =O9*P9 -> 36450
B10: Total | C10: =SUM(_xlfn.ANCHORARRAY(C7)) -> 13752 | E10: =SUM(E7:E9) -> 8000000 | H10: Total | I10: =SUM(_xlfn.ANCHORARRAY(I7)) -> 12280 | K10: =SUM(K7:K9) -> 7000000 | N10: Total | O10: =SUM(_xlfn.ANCHORARRAY(O7)) -> 10808 | Q10: =SUM(Q7:Q9) -> 6000000

Sheet Previsión Ventas
A1: Etiquetas de fila | B1: Recuento distinto de numero_orden | C1: Previsión(Recuento distinto de numero_orden) | D1: Límite de confianza inferior(Recuento distinto de numero_orden) | E1: Límite de confianza superior(Recuento distinto de numero_orden)
A2: 40548 | B2: 5
A3: 40549 | B3: 4
A4: 40550 | B4: 5
A5: 40551 | B5: 2
A6: 40552 | B6: 5
A7: 40553 | B7: 4
A8: 40554 | B8: 3
A9: 40555 | B9: 3
A10: 40556 | B10: 6
A11: 40557 | B11: 3
A12: 40558 | B12: 4
A13: 40559 | B13: 4
... A1127: 41673 | B1127: 23
A1128: 41674 | B1128: 40 | C1128: 40 | D1128: 40 | E1128: 40
A1129: 41675 | C1129: =_xlfn.FORECAST.ETS(A1129,$B$2:$B$1128,$A$2:$A$1128,1,1) -> 40.063568 | D1129: =C1129-_xlfn.FORECAST.ETS.CONFINT(A1129,$B$2:$B$1128,$A$2:$A$1128,0.95,1,1) -> 25.567574 | E1129: =C1129+_xlfn.FORECAST.ETS.CONFINT(A1129,$B$2:$B$1128,$A$2:$A$1128,0.95,1,1) -> 54.559562
A1130: 41676 | C1130: =_xlfn.FORECAST.ETS(A1130,$B$2:$B$1128,$A$2:$A$1128,1,1) -> 40.127137 | D1130: =C1130-_xlfn.FORECAST.ETS.CONFINT(A1130,$B$2:$B$1128,$A$2:$A$1128,0.95,1,1) -> 24.842429 | E1130: =C1130+_xlfn.FORECAST.ETS.CONFINT(A1130,$B$2:$B$1128,$A$2:$A$1128,0.95,1,1) -> 55.411845
A1131: 41677 | C1131: =_xlfn.FORECAST.ETS(A1131,$B$2:$B$1128,$A$2:$A$1128,1,1) -> 40.190705 | D1131: =C1131-_xlfn.FORECAST.ETS.CONFINT(A1131,$B$2:$B$1128,$A$2:$A$1128,0.95,1,1) -> 24.151644 | E1131: =C1131+_xlfn.FORECAST.ETS.CONFINT(A1131,$B$2:$B$1128,$A$2:$A$1128,0.95,1,1) -> 56.229766
A1132: 41678 | C1132: =_xlfn.FORECAST.ETS(A1132,$B$2:$B$1128,$A$2:$A$1128,1,1) -> 40.254274 | D1132: =C1132-_xlfn.FORECAST.ETS.CONFINT(A1132,$B$2:$B$1128,$A$2:$A$1128,0.95,1,1) -> 23.490569 | E1132: =C1132+_xlfn.FORECAST.ETS.CONFINT(A1132,$B$2:$B$1128,$A$2:$A$1128,0.95,1,1) -> 57.017978
A1133: 41679 | C1133: =_xlfn.FORECAST.ETS(A1133,$B$2:$B$1128,$A$2:$A$1128,1,1) -> 40.317842 | D1133: =C1133-_xlfn.FORECAST.ETS.CONFINT(A1133,$B$2:$B$1128,$A$2:$A$1128,0.95,1,1) -> 22.855492 | E1133: =C1133+_xlfn.FORECAST.ETS.CONFINT(A1133,$B$2:$B$1128,$A$2:$A$1128,0.95,1,1) -> 57.780192
A1134: 41680 | C1134: =_xlfn.FORECAST.ETS(A1134,$B$2:$B$1128,$A$2:$A$1128,1,1) -> 40.381411 | D1134: =C1134-_xlfn.FORECAST.ETS.CONFINT(A1134,$B$2:$B$1128,$A$2:$A$1128,0.95,1,1) -> 22.243397 | E1134: =C1134+_xlfn.FORECAST.ETS.CONFINT(A1134,$B$2:$B$1128,$A$2:$A$1128,0.95,1,1) -> 58.519424
A1135: 41681 | C1135: =_xlfn.FORECAST.ETS(A1135,$B$2:$B$1128,$A$2:$A$1128,1,1) -> 40.444979 | D1135: =C1135-_xlfn.FORECAST.ETS.CONFINT(A1135,$B$2:$B$1128,$A$2:$A$1128,0.95,1,1) -> 21.651795 | E1135: =C1135+_xlfn.FORECAST.ETS.CONFINT(A1135,$B$2:$B$1128,$A$2:$A$1128,0.95,1,1) -> 59.238164
A1136: 41682 | C1136: =_xlfn.FORECAST.ETS(A1136,$B$2:$B$1128,$A$2:$A$1128,1,1) -> 40.508548 | D1136: =C1136-_xlfn.FORECAST.ETS.CONFINT(A1136,$B$2:$B$1128,$A$2:$A$1128,0.95,1,1) -> 21.0786 | E1136: =C1136+_xlfn.FORECAST.ETS.CONFINT(A1136,$B$2:$B$1128,$A$2:$A$1128,0.95,1,1) -> 59.938495
A1137: 41683 | C1137: =_xlfn.FORECAST.ETS(A1137,$B$2:$B$1128,$A$2:$A$1128,1,1) -> 40.572116 | D1137: =C1137-_xlfn.FORECAST.ETS.CONFINT(A1137,$B$2:$B$1128,$A$2:$A$1128,0.95,1,1) -> 20.522049 | E1137: =C1137+_xlfn.FORECAST.ETS.CONFINT(A1137,$B$2:$B$1128,$A$2:$A$1128,0.95,1,1) -> 60.622183
A1138: 41684 | C1138: =_xlfn.FORECAST.ETS(A1138,$B$2:$B$1128,$A$2:$A$1128,1,1) -> 40.635684 | D1138: =C1138-_xlfn.FORECAST.ETS.CONFINT(A1138,$B$2:$B$1128,$A$2:$A$1128,0.95,1,1) -> 19.980633 | E1138: =C1138+_xlfn.FORECAST.ETS.CONFINT(A1138,$B$2:$B$1128,$A$2:$A$1128,0.95,1,1) -> 61.290736
A1139: 41685 | C1139: =_xlfn.FORECAST.ETS(A1139,$B$2:$B$1128,$A$2:$A$1128,1,1) -> 40.699253 | D1139: =C1139-_xlfn.FORECAST.ETS.CONFINT(A1139,$B$2:$B$1128,$A$2:$A$1128,0.95,1,1) -> 19.453048 | E1139: =C1139+_xlfn.FORECAST.ETS.CONFINT(A1139,$B$2:$B$1128,$A$2:$A$1128,0.95,1,1) -> 61.945458
A1140: 41686 | C1140: =_xlfn.FORECAST.ETS(A1140,$B$2:$B$1128,$A$2:$A$1128,1,1) -> 40.762821 | D1140: =C1140-_xlfn.FORECAST.ETS.CONFINT(A1140,$B$2:$B$1128,$A$2:$A$1128,0.95,1,1) -> 18.938161 | E1140: =C1140+_xlfn.FORECAST.ETS.CONFINT(A1140,$B$2:$B$1128,$A$2:$A$1128,0.95,1,1) -> 62.587481
... A1458: 42004 | C1458: =_xlfn.FORECAST.ETS(A1458,$B$2:$B$1128,$A$2:$A$1128,1,1) -> 60.977586 | D1458: =C1458-_xlfn.FORECAST.ETS.CONFINT(A1458,$B$2:$B$1128,$A$2:$A$1128,0.95,1,1) -> -73.194607 | E1458: =C1458+_xlfn.FORECAST.ETS.CONFINT(A1458,$B$2:$B$1128,$A$2:$A$1128,0.95,1,1) -> 195.14978

Sheet Optimización Ventas
A1: DATOS RELEVANTES
A5: Etiquetas de fila | B5: Precio Mediano de Producto
A6: Accessories | B6: 10
A7: Bikes | B7: 713
A8: Clothing | B8: 25
A9: Total general | B9: 420
A13: Etiquetas de fila | B13: Cantidad Ordenes
A14: Accessories | B14: 17119
A15: Bikes | B15: 9657
A16: Clothing | B16: 7019
A17: Total general | B17: 21004
A20: SOLUCION USANDO SOLVER
E23: Ventas totales | F23: =SUMPRODUCT(E27:G27,E28:G28) -> 748 | H23: =_xlfn.CONCAT("Ventas Totales"," = ",E28,E26," + ",F28,F26," + ",G28,G26) -> Ventas Totales = 10x + 713y + 25z
A26: Categoría | B26: Ventas | E26: x | F26: y | G26: z
A27: {=A6:A8} -> Accessories | B27: {=B6:B8} -> 10 | C27: x | E27: 1 | F27: 1 | G27: 1
A28: Bikes | B28: 713 | C28: y | E28: =B27 -> 10 | F28: =B28 -> 713 | G28: =B29 -> 25
A29: Clothing | B29: 25 | C29: z
A34: Categoría | B34: Nuevo Stock | D34: Restricciones | E34: x | F34: y | G34: z | H34: valores | I34: ecuación
A35: Accessories | B35: {=B14:B16*1.2} -> 20542.8 | D35: R1 | E35: 1 | F35: 0 | G35: 0 | H35: =SUMPRODUCT($E$27:$G$27,E35:G35) -> 1 | I35: x <= 205,742
A36: Bikes | B36: 11588.4 | D36: R2 | E36: 0 | F36: 1 | G36: 0 | H36: =SUMPRODUCT($E$27:$G$27,E36:G36) -> 1 | I36: y <= 11,588
A37: Clothing | B37: 8422.8 | D37: R3 | E37: 0 | F37: 0 | G37: 1 | H37: =SUMPRODUCT($E$27:$G$27,E37:G37) -> 1 | I37: z <= 8,423
D38: R4 | E38: 1 | F38: 0 | G38: 0 | H38: =SUMPRODUCT($E$27:$G$27,E38:G38) -> 1 | I38: x>= 1000
D39: R5 | E39: 0 | F39: 1 | G39: 0 | H39: =SUMPRODUCT($E$27:$G$27,E39:G39) -> 1 | I39: y>= 1000
D40: R6 | E40: 0 | F40: 0 | G40: 1 | H40: =SUMPRODUCT($E$27:$G$27,E40:G40) -> 1 | I40: z>= 1000
D41: R7 | I41: x,y,z = int
A45: ESTADISTICA DESCRIPTIVA
A49: Cantidad de Pedidos Por Cliente | D49: Montos de Pedidos Por Cliente
A51: Media | B51: 1.5032882 | D51: Media | E51: 1595.5351
A52: Error típico | B52: 0.0081723008 | D52: Error típico | E52: 15.732461
A53: Mediana | B53: 1 | D53: Mediana | E53: 289
A54: Moda | B54: 1 | D54: Moda | E54: 40
A55: Desviación estándar | B55: 1.1085147 | D55: Desviación estándar | E55: 2133.9969
A56: Varianza de la muestra | B56: 1.2288048 | D56: Varianza de la muestra | E56: 4553942.8
A57: Curtosis | B57: 248.75724 | D57: Curtosis | E57: 1.4696652
A58: Coeficiente de asimetría | B58: 12.40327 | D58: Coeficiente de asimetría | E58: 1.4246618
A59: Rango | B59: 27 | D59: Rango | E59: 15996
A60: Mínimo | B60: 1 | D60: Mínimo | E60: 2
A61: Máximo | B61: 28 | D61: Máximo | E61: 15998
A62: Suma | B62: 27659 | D62: Suma | E62: 29356250
... A64: Nivel de confianza(95.0%) | B64: 0.016018469 | D64: Nivel de confianza(95.0%) | E64: 30.837087

Sheet Escenario Agresivo
A1: E
A2: Hoja de cálculo: [Analisis_VentasG2.xlsx]Optimización Ventas
A3: Informe creado: 3/06/2026 15:19:40
A4: Resultado: Solver encontró una solución de enteros dentro de la tolerancia. Se cumplen todas las restricciones.
A5: Motor de Solver
B6: Motor: Simplex LP
B7: Tiempo de la solución: 0.109 segundos.
B8: Iteraciones: 3 Subproblemas: 100
A9: Opciones de Solver
B10: Tiempo máximo Ilimitado, Iteraciones Ilimitado, Precision 0.000001
B11: Máximo de subproblemas Ilimitado, Máximo de soluciones de enteros Ilimitado, Tolerancia de enteros 1%, Asumir no negativo
A14: Celda objetivo (Valor de)
B15: Celda | C15: Nombre | D15: Valor original | E15: Valor final
B16: $F$23 | C16: Ventas totales | D16: 748 | E16: 8000000
A19: Celdas de variables
B20: Celda | C20: Nombre | D20: Valor original | E20: Valor final | F20: Entero
B21: $E$27 | C21: Cant_Accessories | D21: 1 | E21: 1000 | F21: Entero
B22: $F$27 | C22: Cant_Bikes | D22: 1 | E22: 11150 | F22: Entero
B23: $G$27 | C23: Cant_Clothing | D23: 1 | E23: 1602 | F23: Entero
A26: Restricciones
B27: Celda | C27: Nombre | D27: Valor de la celda | E27: Fórmula | F27: Estado | G27: Demora
B28: $H$36 | C28: Cantidad_Bikes | D28: 11150 | E28: $H$36<=11588 | F28: No vinculante | G28: 438
B29: $H$35 | C29: Cantidad_Accessories | D29: 1000 | E29: $H$35<=205742 | F29: No vinculante | G29: 204742
B30: $H$37 | C30: Cantidad_Clothing | D30: 1602 | E30: $H$37<=8423 | F30: No vinculante | G30: 6821
B31: $H$38 | C31: Min_Accessories | D31: 1000 | E31: $H$38>=1000 | F31: Vinculante | G31: 0
B32: $H$39 | C32: Minimo_Bikes | D32: 11150 | E32: $H$39>=1000 | F32: No vinculante | G32: 10150
B33: $H$40 | C33: Minimo_Clothing | D33: 1602 | E33: $H$40>=1000 | F33: No vinculante | G33: 602
B34: $F$23 | C34: Ventas totales | D34: 8000000 | E34: $F$23=8000000 | F34: Vinculante | G34: 0
B35: $E$27:$G$27=Entero

Sheet Escenario Objetivo
A1: Microsoft Excel 16.0 Informe de respuestas
A2: Hoja de cálculo: [Analisis_VentasG2.xlsx]Optimización Ventas
A3: Informe creado: 3/06/2026 15:19:11
A4: Resultado: Solver encontró una solución de enteros dentro de la tolerancia. Se cumplen todas las restricciones.
A5: Motor de Solver
B6: Motor: Simplex LP
B7: Tiempo de la solución: 0.141 segundos.
B8: Iteraciones: 3 Subproblemas: 144
A9: Opciones de Solver
B10: Tiempo máximo Ilimitado, Iteraciones Ilimitado, Precision 0.000001
B11: Máximo de subproblemas Ilimitado, Máximo de soluciones de enteros Ilimitado, Tolerancia de enteros 1%, Asumir no negativo
A14: Celda objetivo (Valor de)
B15: Celda | C15: Nombre | D15: Valor original | E15: Valor final
B16: $F$23 | C16: Ventas totales | D16: 748 | E16: 7000000
A19: Celdas de variables
B20: Celda | C20: Nombre | D20: Valor original | E20: Valor final | F20: Entero
B21: $E$27 | C21: Cant_Accessories | D21: 1 | E21: 1000 | F21: Entero
B22: $F$27 | C22: Cant_Bikes | D22: 1 | E22: 9750 | F22: Entero
B23: $G$27 | C23: Cant_Clothing | D23: 1 | E23: 1530 | F23: Entero
A26: Restricciones
B27: Celda | C27: Nombre | D27: Valor de la celda | E27: Fórmula | F27: Estado | G27: Demora
B28: $H$36 | C28: Cantidad_Bikes | D28: 9750 | E28: $H$36<=11588 | F28: No vinculante | G28: 1838
B29: $H$35 | C29: Cantidad_Accessories | D29: 1000 | E29: $H$35<=205742 | F29: No vinculante | G29: 204742
B30: $H$37 | C30: Cantidad_Clothing | D30: 1530 | E30: $H$37<=8423 | F30: No vinculante | G30: 6893
B31: $H$38 | C31: Min_Accessories | D31: 1000 | E31: $H$38>=1000 | F31: Vinculante | G31: 0
B32: $H$39 | C32: Minimo_Bikes | D32: 9750 | E32: $H$39>=1000 | F32: No vinculante | G32: 8750
B33: $H$40 | C33: Minimo_Clothing | D33: 1530 | E33: $H$40>=1000 | F33: No vinculante | G33: 530
B34: $F$23 | C34: Ventas totales | D34: 7000000 | E34: $F$23=7000000 | F34: Vinculante | G34: 0
B35: $E$27:$G$27=Entero

Sheet Escenario Modesto
A1: Microsoft Excel 16.0 Informe de respuestas
A2: Hoja de cálculo: [Analisis_VentasG2.xlsx]Optimización Ventas
A3: Informe creado: 3/06/2026 15:19:30
A4: Resultado: Solver encontró una solución de enteros dentro de la tolerancia. Se cumplen todas las restricciones.
A5: Motor de Solver
B6: Motor: Simplex LP
B7: Tiempo de la solución: 0.219 segundos.
B8: Iteraciones: 3 Subproblemas: 76
A9: Opciones de Solver
B10: Tiempo máximo Ilimitado, Iteraciones Ilimitado, Precision 0.000001
B11: Máximo de subproblemas Ilimitado, Máximo de soluciones de enteros Ilimitado, Tolerancia de enteros 1%, Asumir no negativo
A14: Celda objetivo (Valor de)
B15: Celda | C15: Nombre | D15: Valor original | E15: Valor final
B16: $F$23 | C16: Ventas totales | D16: 748 | E16: 6000000
A19: Celdas de variables
B20: Celda | C20: Nombre | D20: Valor original | E20: Valor final | F20: Entero
B21: $E$27 | C21: Cant_Accessories | D21: 1 | E21: 1000 | F21: Entero
B22: $F$27 | C22: Cant_Bikes | D22: 1 | E22: 8350 | F22: Entero
B23: $G$27 | C23: Cant_Clothing | D23: 1 | E23: 1458 | F23: Entero
A26: Restricciones
B27: Celda | C27: Nombre | D27: Valor de la celda | E27: Fórmula | F27: Estado | G27: Demora
B28: $H$36 | C28: Cantidad_Bikes | D28: 8350 | E28: $H$36<=11588 | F28: No vinculante | G28: 3238
B29: $H$35 | C29: Cantidad_Accessories | D29: 1000 | E29: $H$35<=205742 | F29: No vinculante | G29: 204742
B30: $H$37 | C30: Cantidad_Clothing | D30: 1458 | E30: $H$37<=8423 | F30: No vinculante | G30: 6965
B31: $H$38 | C31: Min_Accessories | D31: 1000 | E31: $H$38>=1000 | F31: Vinculante | G31: 0
B32: $H$39 | C32: Minimo_Bikes | D32: 8350 | E32: $H$39>=1000 | F32: No vinculante | G32: 7350
B33: $H$40 | C33: Minimo_Clothing | D33: 1458 | E33: $H$40>=1000 | F33: No vinculante | G33: 458
B34: $F$23 | C34: Ventas totales | D34: 6000000 | E34: $F$23=6000000 | F34: Vinculante | G34: 0
B35: $E$27:$G$27=Entero
